LICENSE
README.md
nautobot_ssot_vsphere/__init__.py
nautobot_ssot_vsphere/diffsync/__init__.py
nautobot_ssot_vsphere/diffsync/adapters/__init__.py
nautobot_ssot_vsphere/diffsync/adapters/adapter_nautobot.py
nautobot_ssot_vsphere/diffsync/adapters/adapter_vsphere.py
nautobot_ssot_vsphere/diffsync/adapters/shared/__init__.py
nautobot_ssot_vsphere/diffsync/adapters/shared/adapter_shared.py
nautobot_ssot_vsphere/diffsync/defaults.py
nautobot_ssot_vsphere/diffsync/diffsync_models.py
nautobot_ssot_vsphere/jobs.py
nautobot_ssot_vsphere/management/__init__.py
nautobot_ssot_vsphere/management/commands/__init__.py
nautobot_ssot_vsphere/management/commands/create_env.py
nautobot_ssot_vsphere/signals.py
nautobot_ssot_vsphere/static/nautobot_ssot_vsphere/vmware.png
nautobot_ssot_vsphere/tests/__init__.py
nautobot_ssot_vsphere/tests/fixtures/__init__.py
nautobot_ssot_vsphere/tests/fixtures/get_cluster_details.json
nautobot_ssot_vsphere/tests/fixtures/get_clusters.json
nautobot_ssot_vsphere/tests/fixtures/get_datacenters.json
nautobot_ssot_vsphere/tests/fixtures/get_dc_details.json
nautobot_ssot_vsphere/tests/fixtures/get_host_details.json
nautobot_ssot_vsphere/tests/fixtures/get_host_from_cluster.json
nautobot_ssot_vsphere/tests/fixtures/get_vm_details.json
nautobot_ssot_vsphere/tests/fixtures/get_vm_interfaces.json
nautobot_ssot_vsphere/tests/fixtures/get_vm_interfaces_1.json
nautobot_ssot_vsphere/tests/fixtures/get_vms.json
nautobot_ssot_vsphere/tests/fixtures/get_vms_from_cluster.json
nautobot_ssot_vsphere/tests/fixtures/get_vms_from_dc.json
nautobot_ssot_vsphere/tests/fixtures/nautobot_fixtures.py
nautobot_ssot_vsphere/tests/fixtures/utilities.py
nautobot_ssot_vsphere/tests/test_api.py
nautobot_ssot_vsphere/tests/test_basic.py
nautobot_ssot_vsphere/tests/test_vsphere_client.py
nautobot_ssot_vsphere/utilities/__init__.py
nautobot_ssot_vsphere/utilities/nautobot_utils.py
nautobot_ssot_vsphere/utilities/vsphere_client.py
nautobot_ssot_vsphere-0.1.4.dist-info/LICENSE
nautobot_ssot_vsphere-0.1.4.dist-info/WHEEL
nautobot_ssot_vsphere-0.1.4.dist-info/METADATA
nautobot_ssot_vsphere-0.1.4.dist-info/RECORD
