Metadata-Version: 2.1
Name: nautobot-ssot-vsphere
Version: 0.1.4
Summary: Nautobot SSoT vSphere
Home-page: https://github.com/h4ndzdatm0ld/nautobot-ssot-vsphere
License: Apache-2.0
Keywords: nautobot,nautobot-plugin,ssot,diffsync,vsphere,vmware,virtualization
Author: h4ndzdatm0ld
Author-email: hugotinoco@icloud.com
Requires-Python: >=3.7,<4.0
Classifier: License :: OSI Approved :: Apache Software License
Classifier: Programming Language :: Python :: 3
Classifier: Programming Language :: Python :: 3.7
Classifier: Programming Language :: Python :: 3.8
Classifier: Programming Language :: Python :: 3.9
Classifier: Programming Language :: Python :: 3.10
Classifier: Programming Language :: Python :: 3.11
Provides-Extra: nautobot
Requires-Dist: diffsync (>=1.4.3,<2.0.0)
Requires-Dist: nautobot-ssot (>=1.1.0,<2.0.0)
Requires-Dist: netutils (>=1.1.0,<2.0.0)
Project-URL: Repository, https://github.com/h4ndzdatm0ld/nautobot-ssot-vsphere
